[
	{
		"inputs": [
			{
				"internalType": "bytes",
				"name": "",
				"type": "bytes"
			}
		],
		"name": "checkUpkeep",
		"outputs": [
			{
				"internalType": "bool",
				"name": "upkeepNeeded",
				"type": "bool"
			},
			{
				"internalType": "bytes",
				"name": "performData",
				"type": "bytes"
			}
		],
		"stateMutability": "nonpayable",
		"type": "function"
	},
	{
		"inputs": [
			{
				"internalType": "bytes",
				"name": "performData",
				"type": "bytes"
			}
		],
		"name": "performUpkeep",
		"outputs": [],
		"stateMutability": "nonpayable",
		"type": "function"
	},
	{
		"inputs": [
			{
				"internalType": "uint256",
				"name": "_positionId",
				"type": "uint256"
			},
			{
				"internalType": "uint256",
				"name": "_stopLoss",
				"type": "uint256"
			},
			{
				"internalType": "uint256",
				"name": "_takeProfit",
				"type": "uint256"
			}
		],
		"name": "setSLTP",
		"outputs": [],
		"stateMutability": "nonpayable",
		"type": "function"
	},
	{
		"inputs": [
			{
				"internalType": "address",
				"name": "_futuresContract",
				"type": "address"
			}
		],
		"stateMutability": "nonpayable",
		"type": "constructor"
	},
	{
		"anonymous": false,
		"inputs": [
			{
				"indexed": true,
				"internalType": "uint256",
				"name": "positionId",
				"type": "uint256"
			},
			{
				"indexed": true,
				"internalType": "address",
				"name": "trader",
				"type": "address"
			},
			{
				"indexed": false,
				"internalType": "string",
				"name": "action",
				"type": "string"
			}
		],
		"name": "SLTPExecuted",
		"type": "event"
	},
	{
		"anonymous": false,
		"inputs": [
			{
				"indexed": true,
				"internalType": "uint256",
				"name": "positionId",
				"type": "uint256"
			},
			{
				"indexed": true,
				"internalType": "address",
				"name": "trader",
				"type": "address"
			},
			{
				"indexed": false,
				"internalType": "uint256",
				"name": "stopLoss",
				"type": "uint256"
			},
			{
				"indexed": false,
				"internalType": "uint256",
				"name": "takeProfit",
				"type": "uint256"
			}
		],
		"name": "SLTPSet",
		"type": "event"
	},
	{
		"inputs": [
			{
				"internalType": "uint256",
				"name": "",
				"type": "uint256"
			}
		],
		"name": "activePositions",
		"outputs": [
			{
				"internalType": "uint256",
				"name": "",
				"type": "uint256"
			}
		],
		"stateMutability": "view",
		"type": "function"
	},
	{
		"inputs": [],
		"name": "futuresContract",
		"outputs": [
			{
				"internalType": "contract IfutureLongShort",
				"name": "",
				"type": "address"
			}
		],
		"stateMutability": "view",
		"type": "function"
	},
	{
		"inputs": [
			{
				"internalType": "uint256",
				"name": "",
				"type": "uint256"
			}
		],
		"name": "sLTPOrders",
		"outputs": [
			{
				"internalType": "address",
				"name": "trader",
				"type": "address"
			},
			{
				"internalType": "uint256",
				"name": "stopLoss",
				"type": "uint256"
			},
			{
				"internalType": "uint256",
				"name": "takeProfit",
				"type": "uint256"
			},
			{
				"internalType": "bool",
				"name": "isActive",
				"type": "bool"
			}
		],
		"stateMutability": "view",
		"type": "function"
	}
]